{"commitInfo":{"timestamp":1747893047437,"operation":"WRITE","operationParameters":{"mode":"Append","partitionBy":"[]"},"readVersion":238,"isolationLevel":"Serializable","isBlindAppend":true,"operationMetrics":{"numFiles":"2","numOutputRows":"1","numOutputBytes":"566226"},"engineInfo":"Apache-Spark/3.5.5 Delta-Lake/3.3.1","txnId":"ee2869fa-40f7-4433-b2de-e0c68ba61056"}}
{"add":{"path":"part-00007-663eddf8-c0b4-40d7-a734-5d4ee9085d57-c000.snappy.parquet","partitionValues":{},"size":565741,"modificationTime":1747893047402,"dataChange":true,"stats":"{\"numRecords\":1,\"minValues\":{\"sno\":\"239\",\"filename\":\"pg1226.txt\",\"content\":\"﻿The Project Gutenberg eBook of \"},\"maxValues\":{\"sno\":\"239\",\"filename\":\"pg1226.txt\",\"content\":\"﻿The Project Gutenberg eBook of \"},\"nullCount\":{\"sno\":0,\"filename\":0,\"content\":0}}"}}
