{"commitInfo":{"timestamp":1747894412907,"operation":"WRITE","operationParameters":{"mode":"Append","partitionBy":"[]"},"readVersion":1490,"isolationLevel":"Serializable","isBlindAppend":true,"operationMetrics":{"numFiles":"2","numOutputRows":"1","numOutputBytes":"50515"},"engineInfo":"Apache-Spark/3.5.5 Delta-Lake/3.3.1","txnId":"013d3b36-192b-4c72-b32e-1585c5a4db41"}}
{"add":{"path":"part-00007-1829c98d-6b07-464c-a0bf-aaa76774623f-c000.snappy.parquet","partitionValues":{},"size":50030,"modificationTime":1747894412891,"dataChange":true,"stats":"{\"numRecords\":1,\"minValues\":{\"sno\":\"1232\",\"filename\":\"pg61.txt\",\"content\":\"﻿The Project Gutenberg eBook of \"},\"maxValues\":{\"sno\":\"1232\",\"filename\":\"pg61.txt\",\"content\":\"﻿The Project Gutenberg eBook of \"},\"nullCount\":{\"sno\":0,\"filename\":0,\"content\":0}}"}}
