{"commitInfo":{"timestamp":1747894881270,"operation":"WRITE","operationParameters":{"mode":"Append","partitionBy":"[]"},"readVersion":2133,"isolationLevel":"Serializable","isBlindAppend":true,"operationMetrics":{"numFiles":"2","numOutputRows":"1","numOutputBytes":"422222"},"engineInfo":"Apache-Spark/3.5.5 Delta-Lake/3.3.1","txnId":"fe0620b1-d415-4afc-b4ad-f854c91235dc"}}
{"add":{"path":"part-00007-58ba2019-ca5f-4099-8c91-a627bd6e827d-c000.snappy.parquet","partitionValues":{},"size":421737,"modificationTime":1747894881246,"dataChange":true,"stats":"{\"numRecords\":1,\"minValues\":{\"sno\":\"1875\",\"filename\":\"pg331.txt\",\"content\":\"﻿The Project Gutenberg eBook of \"},\"maxValues\":{\"sno\":\"1875\",\"filename\":\"pg331.txt\",\"content\":\"﻿The Project Gutenberg eBook of \"},\"nullCount\":{\"sno\":0,\"filename\":0,\"content\":0}}"}}
