{"commitInfo":{"timestamp":1747894339178,"operation":"WRITE","operationParameters":{"mode":"Append","partitionBy":"[]"},"readVersion":1387,"isolationLevel":"Serializable","isBlindAppend":true,"operationMetrics":{"numFiles":"2","numOutputRows":"1","numOutputBytes":"280768"},"engineInfo":"Apache-Spark/3.5.5 Delta-Lake/3.3.1","txnId":"ee23e0d1-41be-4811-bf37-2c39cd5ef901"}}
{"add":{"path":"part-00007-a5815841-4dd3-4bb8-bef0-fb420c1131aa-c000.snappy.parquet","partitionValues":{},"size":280283,"modificationTime":1747894339159,"dataChange":true,"stats":"{\"numRecords\":1,\"minValues\":{\"sno\":\"1129\",\"filename\":\"pg1036.txt\",\"content\":\"﻿The Project Gutenberg eBook of \"},\"maxValues\":{\"sno\":\"1129\",\"filename\":\"pg1036.txt\",\"content\":\"﻿The Project Gutenberg eBook of \"},\"nullCount\":{\"sno\":0,\"filename\":0,\"content\":0}}"}}
