{"commitInfo":{"timestamp":1747894189407,"operation":"WRITE","operationParameters":{"mode":"Append","partitionBy":"[]"},"readVersion":1170,"isolationLevel":"Serializable","isBlindAppend":true,"operationMetrics":{"numFiles":"2","numOutputRows":"1","numOutputBytes":"82819"},"engineInfo":"Apache-Spark/3.5.5 Delta-Lake/3.3.1","txnId":"7469d1e0-171f-4d4d-baac-eae5d644c0de"}}
{"add":{"path":"part-00007-36d3bfdd-40d2-417f-bc84-90d6726d87db-c000.snappy.parquet","partitionValues":{},"size":82334,"modificationTime":1747894189345,"dataChange":true,"stats":"{\"numRecords\":1,\"minValues\":{\"sno\":\"912\",\"filename\":\"pg59.txt\",\"content\":\"﻿The Project Gutenberg eBook of \"},\"maxValues\":{\"sno\":\"912\",\"filename\":\"pg59.txt\",\"content\":\"﻿The Project Gutenberg eBook of \"},\"nullCount\":{\"sno\":0,\"filename\":0,\"content\":0}}"}}
