{"commitInfo":{"timestamp":1747894500950,"operation":"WRITE","operationParameters":{"mode":"Append","partitionBy":"[]"},"readVersion":1616,"isolationLevel":"Serializable","isBlindAppend":true,"operationMetrics":{"numFiles":"2","numOutputRows":"1","numOutputBytes":"50864"},"engineInfo":"Apache-Spark/3.5.5 Delta-Lake/3.3.1","txnId":"1e42dc7d-6a52-4fe6-b6bc-cfa4db41f97b"}}
{"add":{"path":"part-00007-91b25768-3c5d-47c0-a48a-7f4d89ad75e6-c000.snappy.parquet","partitionValues":{},"size":50379,"modificationTime":1747894500925,"dataChange":true,"stats":"{\"numRecords\":1,\"minValues\":{\"sno\":\"1358\",\"filename\":\"pg333.txt\",\"content\":\"﻿The Project Gutenberg eBook of \"},\"maxValues\":{\"sno\":\"1358\",\"filename\":\"pg333.txt\",\"content\":\"﻿The Project Gutenberg eBook of \"},\"nullCount\":{\"sno\":0,\"filename\":0,\"content\":0}}"}}
