{"commitInfo":{"timestamp":1747894688666,"operation":"WRITE","operationParameters":{"mode":"Append","partitionBy":"[]"},"readVersion":1874,"isolationLevel":"Serializable","isBlindAppend":true,"operationMetrics":{"numFiles":"2","numOutputRows":"1","numOutputBytes":"181785"},"engineInfo":"Apache-Spark/3.5.5 Delta-Lake/3.3.1","txnId":"0ceecdc0-f14f-4799-a523-0ca53ec949fe"}}
{"add":{"path":"part-00007-d24e85e7-4ffd-4f4a-882b-cb992e347975-c000.snappy.parquet","partitionValues":{},"size":181300,"modificationTime":1747894688642,"dataChange":true,"stats":"{\"numRecords\":1,\"minValues\":{\"sno\":\"1616\",\"filename\":\"pg530.txt\",\"content\":\"﻿The Project Gutenberg eBook of \"},\"maxValues\":{\"sno\":\"1616\",\"filename\":\"pg530.txt\",\"content\":\"﻿The Project Gutenberg eBook of \"},\"nullCount\":{\"sno\":0,\"filename\":0,\"content\":0}}"}}
