{"commitInfo":{"timestamp":1747894067328,"operation":"WRITE","operationParameters":{"mode":"Append","partitionBy":"[]"},"readVersion":984,"isolationLevel":"Serializable","isBlindAppend":true,"operationMetrics":{"numFiles":"2","numOutputRows":"1","numOutputBytes":"139031"},"engineInfo":"Apache-Spark/3.5.5 Delta-Lake/3.3.1","txnId":"9fc96728-4c59-40c9-abe0-62181c714d63"}}
{"add":{"path":"part-00007-e0ffd386-3ae2-4945-b82d-289f3506738c-c000.snappy.parquet","partitionValues":{},"size":138546,"modificationTime":1747894067297,"dataChange":true,"stats":"{\"numRecords\":1,\"minValues\":{\"sno\":\"726\",\"filename\":\"pg171.txt\",\"content\":\"﻿The Project Gutenberg eBook of \"},\"maxValues\":{\"sno\":\"726\",\"filename\":\"pg171.txt\",\"content\":\"﻿The Project Gutenberg eBook of \"},\"nullCount\":{\"sno\":0,\"filename\":0,\"content\":0}}"}}
