{"commitInfo":{"timestamp":1747893510627,"operation":"WRITE","operationParameters":{"mode":"Append","partitionBy":"[]"},"readVersion":380,"isolationLevel":"Serializable","isBlindAppend":true,"operationMetrics":{"numFiles":"2","numOutputRows":"1","numOutputBytes":"493537"},"engineInfo":"Apache-Spark/3.5.5 Delta-Lake/3.3.1","txnId":"d97f4ce2-7234-4735-aa71-69b0d16b85c1"}}
{"add":{"path":"part-00007-423b876b-3178-473b-be56-85e9f4eb4dc4-c000.snappy.parquet","partitionValues":{},"size":493052,"modificationTime":1747893510553,"dataChange":true,"stats":"{\"numRecords\":1,\"minValues\":{\"sno\":\"122\",\"filename\":\"pg601.txt\",\"content\":\"﻿The Project Gutenberg eBook of \"},\"maxValues\":{\"sno\":\"122\",\"filename\":\"pg601.txt\",\"content\":\"﻿The Project Gutenberg eBook of \"},\"nullCount\":{\"sno\":0,\"filename\":0,\"content\":0}}"}}
