{"commitInfo":{"timestamp":1747893612560,"operation":"WRITE","operationParameters":{"mode":"Append","partitionBy":"[]"},"readVersion":486,"isolationLevel":"Serializable","isBlindAppend":true,"operationMetrics":{"numFiles":"2","numOutputRows":"1","numOutputBytes":"83534"},"engineInfo":"Apache-Spark/3.5.5 Delta-Lake/3.3.1","txnId":"bc3bc710-f8b1-41fd-ad0f-15cd217ffd5c"}}
{"add":{"path":"part-00007-be775c8c-fb31-44e7-b998-2f45ee2b06ec-c000.snappy.parquet","partitionValues":{},"size":83049,"modificationTime":1747893612535,"dataChange":true,"stats":"{\"numRecords\":1,\"minValues\":{\"sno\":\"228\",\"filename\":\"pg389.txt\",\"content\":\"﻿The Project Gutenberg eBook of \"},\"maxValues\":{\"sno\":\"228\",\"filename\":\"pg389.txt\",\"content\":\"﻿The Project Gutenberg eBook of \"},\"nullCount\":{\"sno\":0,\"filename\":0,\"content\":0}}"}}
