{"commitInfo":{"timestamp":1747893619718,"operation":"WRITE","operationParameters":{"mode":"Append","partitionBy":"[]"},"readVersion":492,"isolationLevel":"Serializable","isBlindAppend":true,"operationMetrics":{"numFiles":"2","numOutputRows":"1","numOutputBytes":"372707"},"engineInfo":"Apache-Spark/3.5.5 Delta-Lake/3.3.1","txnId":"363eaa73-946b-4512-b78c-d465829694ba"}}
{"add":{"path":"part-00007-87e8a46b-66b9-4fda-b337-8665cb08c1d2-c000.snappy.parquet","partitionValues":{},"size":372222,"modificationTime":1747893619696,"dataChange":true,"stats":"{\"numRecords\":1,\"minValues\":{\"sno\":\"234\",\"filename\":\"pg1300.txt\",\"content\":\"﻿The Project Gutenberg eBook of \"},\"maxValues\":{\"sno\":\"234\",\"filename\":\"pg1300.txt\",\"content\":\"﻿The Project Gutenberg eBook of \"},\"nullCount\":{\"sno\":0,\"filename\":0,\"content\":0}}"}}
