{"commitInfo":{"timestamp":1747894909508,"operation":"WRITE","operationParameters":{"mode":"Append","partitionBy":"[]"},"readVersion":2165,"isolationLevel":"Serializable","isBlindAppend":true,"operationMetrics":{"numFiles":"2","numOutputRows":"1","numOutputBytes":"158347"},"engineInfo":"Apache-Spark/3.5.5 Delta-Lake/3.3.1","txnId":"b3b692c4-356a-4c03-bdb2-6cef49810346"}}
{"add":{"path":"part-00007-fdf5a7a6-11a3-462b-aae7-eaaaf2eafbad-c000.snappy.parquet","partitionValues":{},"size":157862,"modificationTime":1747894909467,"dataChange":true,"stats":"{\"numRecords\":1,\"minValues\":{\"sno\":\"1907\",\"filename\":\"pg1877.txt\",\"content\":\"﻿The Project Gutenberg eBook of \"},\"maxValues\":{\"sno\":\"1907\",\"filename\":\"pg1877.txt\",\"content\":\"﻿The Project Gutenberg eBook of \"},\"nullCount\":{\"sno\":0,\"filename\":0,\"content\":0}}"}}
