{"commitInfo":{"timestamp":1747894266981,"operation":"WRITE","operationParameters":{"mode":"Append","partitionBy":"[]"},"readVersion":1284,"isolationLevel":"Serializable","isBlindAppend":true,"operationMetrics":{"numFiles":"2","numOutputRows":"1","numOutputBytes":"176437"},"engineInfo":"Apache-Spark/3.5.5 Delta-Lake/3.3.1","txnId":"07642df9-7f2b-4149-af6b-53418c450f97"}}
{"add":{"path":"part-00007-c005266a-ad8e-4208-9541-5e4089843260-c000.snappy.parquet","partitionValues":{},"size":175952,"modificationTime":1747894266945,"dataChange":true,"stats":"{\"numRecords\":1,\"minValues\":{\"sno\":\"1026\",\"filename\":\"pg339.txt\",\"content\":\"﻿The Project Gutenberg eBook of \"},\"maxValues\":{\"sno\":\"1026\",\"filename\":\"pg339.txt\",\"content\":\"﻿The Project Gutenberg eBook of \"},\"nullCount\":{\"sno\":0,\"filename\":0,\"content\":0}}"}}
