{"commitInfo":{"timestamp":1747892957090,"operation":"WRITE","operationParameters":{"mode":"Append","partitionBy":"[]"},"readVersion":226,"isolationLevel":"Serializable","isBlindAppend":true,"operationMetrics":{"numFiles":"2","numOutputRows":"1","numOutputBytes":"49698"},"engineInfo":"Apache-Spark/3.5.5 Delta-Lake/3.3.1","txnId":"d8b0f7ee-9e66-43a5-a8cb-df1f3b8a5e7b"}}
{"add":{"path":"part-00007-c1fdb546-84da-4988-a2b3-1b98f047fce2-c000.snappy.parquet","partitionValues":{},"size":49213,"modificationTime":1747892957066,"dataChange":true,"stats":"{\"numRecords\":1,\"minValues\":{\"sno\":\"227\",\"filename\":\"pg410.txt\",\"content\":\"﻿The Project Gutenberg eBook of \"},\"maxValues\":{\"sno\":\"227\",\"filename\":\"pg410.txt\",\"content\":\"﻿The Project Gutenberg eBook of \"},\"nullCount\":{\"sno\":0,\"filename\":0,\"content\":0}}"}}
