{"commitInfo":{"timestamp":1747894332250,"operation":"WRITE","operationParameters":{"mode":"Append","partitionBy":"[]"},"readVersion":1377,"isolationLevel":"Serializable","isBlindAppend":true,"operationMetrics":{"numFiles":"2","numOutputRows":"1","numOutputBytes":"96933"},"engineInfo":"Apache-Spark/3.5.5 Delta-Lake/3.3.1","txnId":"ccd07bc3-cc31-49e9-8b12-1cbfa7190148"}}
{"add":{"path":"part-00007-877304ee-a462-4370-9c30-b01f0b9040c7-c000.snappy.parquet","partitionValues":{},"size":96448,"modificationTime":1747894332179,"dataChange":true,"stats":"{\"numRecords\":1,\"minValues\":{\"sno\":\"1119\",\"filename\":\"pg585.txt\",\"content\":\"﻿The Project Gutenberg eBook of \"},\"maxValues\":{\"sno\":\"1119\",\"filename\":\"pg585.txt\",\"content\":\"﻿The Project Gutenberg eBook of \"},\"nullCount\":{\"sno\":0,\"filename\":0,\"content\":0}}"}}
