{"commitInfo":{"timestamp":1747894574541,"operation":"WRITE","operationParameters":{"mode":"Append","partitionBy":"[]"},"readVersion":1718,"isolationLevel":"Serializable","isBlindAppend":true,"operationMetrics":{"numFiles":"2","numOutputRows":"1","numOutputBytes":"246858"},"engineInfo":"Apache-Spark/3.5.5 Delta-Lake/3.3.1","txnId":"e9b21ad3-6a53-40f0-b434-d105a535d93d"}}
{"add":{"path":"part-00007-0e0241a2-d55a-432a-941e-3e442fcfbd22-c000.snappy.parquet","partitionValues":{},"size":246373,"modificationTime":1747894574475,"dataChange":true,"stats":"{\"numRecords\":1,\"minValues\":{\"sno\":\"1460\",\"filename\":\"pg538.txt\",\"content\":\"﻿The Project Gutenberg eBook of \"},\"maxValues\":{\"sno\":\"1460\",\"filename\":\"pg538.txt\",\"content\":\"﻿The Project Gutenberg eBook of \"},\"nullCount\":{\"sno\":0,\"filename\":0,\"content\":0}}"}}
