{"commitInfo":{"timestamp":1747894443325,"operation":"WRITE","operationParameters":{"mode":"Append","partitionBy":"[]"},"readVersion":1534,"isolationLevel":"Serializable","isBlindAppend":true,"operationMetrics":{"numFiles":"2","numOutputRows":"1","numOutputBytes":"232025"},"engineInfo":"Apache-Spark/3.5.5 Delta-Lake/3.3.1","txnId":"48c53fe1-b71e-41b6-a344-711f4f4601c3"}}
{"add":{"path":"part-00007-f610abad-d785-4d9f-ae27-d92c4392b2c3-c000.snappy.parquet","partitionValues":{},"size":231540,"modificationTime":1747894443298,"dataChange":true,"stats":"{\"numRecords\":1,\"minValues\":{\"sno\":\"1276\",\"filename\":\"pg1159.txt\",\"content\":\"﻿The Project Gutenberg eBook of \"},\"maxValues\":{\"sno\":\"1276\",\"filename\":\"pg1159.txt\",\"content\":\"﻿The Project Gutenberg eBook of \"},\"nullCount\":{\"sno\":0,\"filename\":0,\"content\":0}}"}}
