{"commitInfo":{"timestamp":1747894645263,"operation":"WRITE","operationParameters":{"mode":"Append","partitionBy":"[]"},"readVersion":1814,"isolationLevel":"Serializable","isBlindAppend":true,"operationMetrics":{"numFiles":"2","numOutputRows":"1","numOutputBytes":"190708"},"engineInfo":"Apache-Spark/3.5.5 Delta-Lake/3.3.1","txnId":"e414cb73-4bf4-45e0-90c0-95f74b7e4745"}}
{"add":{"path":"part-00007-e5b71738-1726-4aeb-b4af-3b6ef2d613fe-c000.snappy.parquet","partitionValues":{},"size":190223,"modificationTime":1747894645256,"dataChange":true,"stats":"{\"numRecords\":1,\"minValues\":{\"sno\":\"1556\",\"filename\":\"pg2015.txt\",\"content\":\"﻿The Project Gutenberg eBook of \"},\"maxValues\":{\"sno\":\"1556\",\"filename\":\"pg2015.txt\",\"content\":\"﻿The Project Gutenberg eBook of \"},\"nullCount\":{\"sno\":0,\"filename\":0,\"content\":0}}"}}
