{"commitInfo":{"timestamp":1747893699673,"operation":"WRITE","operationParameters":{"mode":"Append","partitionBy":"[]"},"readVersion":574,"isolationLevel":"Serializable","isBlindAppend":true,"operationMetrics":{"numFiles":"2","numOutputRows":"1","numOutputBytes":"101866"},"engineInfo":"Apache-Spark/3.5.5 Delta-Lake/3.3.1","txnId":"aa3725d6-62d0-4629-a04a-c2b0bebeb251"}}
{"add":{"path":"part-00007-951083f7-9c63-4ee3-87da-aef1a6bbb0ea-c000.snappy.parquet","partitionValues":{},"size":101381,"modificationTime":1747893699625,"dataChange":true,"stats":"{\"numRecords\":1,\"minValues\":{\"sno\":\"316\",\"filename\":\"pg607.txt\",\"content\":\"﻿The Project Gutenberg eBook of \"},\"maxValues\":{\"sno\":\"316\",\"filename\":\"pg607.txt\",\"content\":\"﻿The Project Gutenberg eBook of \"},\"nullCount\":{\"sno\":0,\"filename\":0,\"content\":0}}"}}
