{"commitInfo":{"timestamp":1747894147626,"operation":"WRITE","operationParameters":{"mode":"Append","partitionBy":"[]"},"readVersion":1107,"isolationLevel":"Serializable","isBlindAppend":true,"operationMetrics":{"numFiles":"2","numOutputRows":"1","numOutputBytes":"206220"},"engineInfo":"Apache-Spark/3.5.5 Delta-Lake/3.3.1","txnId":"010e41f0-3c2e-4524-928b-609cc852ba3a"}}
{"add":{"path":"part-00007-acd021d9-e35e-4b3c-a94b-2473c78b837b-c000.snappy.parquet","partitionValues":{},"size":205735,"modificationTime":1747894147607,"dataChange":true,"stats":"{\"numRecords\":1,\"minValues\":{\"sno\":\"849\",\"filename\":\"pg784.txt\",\"content\":\"﻿The Project Gutenberg eBook of \"},\"maxValues\":{\"sno\":\"849\",\"filename\":\"pg784.txt\",\"content\":\"﻿The Project Gutenberg eBook of \"},\"nullCount\":{\"sno\":0,\"filename\":0,\"content\":0}}"}}
