{"commitInfo":{"timestamp":1747893440240,"operation":"WRITE","operationParameters":{"mode":"Append","partitionBy":"[]"},"readVersion":308,"isolationLevel":"Serializable","isBlindAppend":true,"operationMetrics":{"numFiles":"2","numOutputRows":"1","numOutputBytes":"308731"},"engineInfo":"Apache-Spark/3.5.5 Delta-Lake/3.3.1","txnId":"d6b89dd4-76a4-4256-9089-4d0e3b17c9e6"}}
{"add":{"path":"part-00007-0f835398-8548-4d9e-b827-88bdacf66a90-c000.snappy.parquet","partitionValues":{},"size":308246,"modificationTime":1747893440204,"dataChange":true,"stats":"{\"numRecords\":1,\"minValues\":{\"sno\":\"50\",\"filename\":\"pg546.txt\",\"content\":\"﻿The Project Gutenberg eBook of \"},\"maxValues\":{\"sno\":\"50\",\"filename\":\"pg546.txt\",\"content\":\"﻿The Project Gutenberg eBook of \"},\"nullCount\":{\"sno\":0,\"filename\":0,\"content\":0}}"}}
