{"commitInfo":{"timestamp":1747893998892,"operation":"WRITE","operationParameters":{"mode":"Append","partitionBy":"[]"},"readVersion":877,"isolationLevel":"Serializable","isBlindAppend":true,"operationMetrics":{"numFiles":"2","numOutputRows":"1","numOutputBytes":"361797"},"engineInfo":"Apache-Spark/3.5.5 Delta-Lake/3.3.1","txnId":"e0be7a40-b112-4a9b-992b-5f96e3a52241"}}
{"add":{"path":"part-00007-3413bb21-eb58-4cc8-88ee-1c80227acdfc-c000.snappy.parquet","partitionValues":{},"size":361312,"modificationTime":1747893998867,"dataChange":true,"stats":"{\"numRecords\":1,\"minValues\":{\"sno\":\"619\",\"filename\":\"pg565.txt\",\"content\":\"﻿The Project Gutenberg eBook of \"},\"maxValues\":{\"sno\":\"619\",\"filename\":\"pg565.txt\",\"content\":\"﻿The Project Gutenberg eBook of \"},\"nullCount\":{\"sno\":0,\"filename\":0,\"content\":0}}"}}
